README
setup.py
isimage/Image.py
isimage/__init__.py
isimage/adaptive_affinity_propagation_.py
isimage/cluster_patterns.py
isimage/extract_pattern.py
isimage/find_embryo.py
isimage.egg-info/PKG-INFO
isimage.egg-info/SOURCES.txt
isimage.egg-info/dependency_links.txt
isimage.egg-info/entry_points.txt
isimage.egg-info/requires.txt
isimage.egg-info/top_level.txt
isimage/analyse_image/__init__.py
isimage/analyse_image/analyse_image.py
isimage/analyse_image/test_images/17-BLIMP-DOR003.jpg
isimage/analyse_image/test_images/26-cotransporter-003.jpg
isimage/analyse_image/test_images/31-Meis1-002.jpg
isimage/analyse_image/test_images/5D9_30_lattot_R10
isimage/analyse_image/test_images/Xt_TGas056e20_NF09_1_lat2.gif
isimage/analyse_image/test_images/Xt_TGas060f16_NF28_1_left.gif
isimage/select_images/GeneStage.py
isimage/select_images/__init__.py
isimage/select_images/check_cleared.py
isimage/select_images/cleared_model.dump
isimage/select_images/create_report.py
isimage/select_images/markup.py
isimage/select_images/score_images.py
isimage/select_images/select_images.py
isimage/select_images/test_tasks.txt
isimage/select_images/test_images/CBFb/17-CBFb-001.jpg
isimage/select_images/test_images/CBFb/17-CBFb-002.jpg
isimage/select_images/test_images/CBFb/17-CBFb-003.jpg
isimage/select_images/test_images/CBFb/17-CBFb-004.jpg
isimage/select_images/test_images/CBFb/17-CBFb-005.jpg
isimage/select_images/test_images/CBFb/17-CBFb-006.jpg
isimage/select_images/test_images/CBFb/17-CBFb-007.jpg
isimage/select_images/test_images/CBFb/17-CBFb-008.jpg
isimage/select_images/test_images/CBFb/17-CBFb-009.jpg
isimage/select_images/test_images/CBFb/17-CBFb-010.jpg
isimage/select_images/test_images/CBFb/17-CBFb-011.jpg
isimage/select_images/test_images/CBFb/17-CBFb-012.jpg
isimage/select_images/test_images/CBFb/17-CBFb-013.jpg
isimage/select_images/test_images/CBFb/17-CBFb-014.jpg
isimage/select_images/test_images/CBFb/17-CBFb-015.jpg
isimage/select_images/test_images/CBFb/17-CBFb-016.jpg
isimage/select_images/test_images/CBFb/17-CBFb-017.jpg
isimage/select_images/test_images/CBFb/17-CBFb-018.jpg
isimage/select_images/test_images/CBFb/17-CBFb-019.jpg
