Metadata-Version: 1.0
Name: isimage
Version: 0.1.2
Summary: A module and scripts for analysis of whole-mount in-situ hybridisation images.
Home-page: https://github.com/ilyapatrushev/isimage
Author: Ilya Patrushev
Author-email: ilya.patrushev@gmail.com
License: GPL v2.0
Platform: UNKNOWN
